MANIFEST.in
README.md
requirements.txt
setup.py
src/pwbm_sp_dev.egg-info/PKG-INFO
src/pwbm_sp_dev.egg-info/SOURCES.txt
src/pwbm_sp_dev.egg-info/dependency_links.txt
src/pwbm_sp_dev.egg-info/entry_points.txt
src/pwbm_sp_dev.egg-info/requires.txt
src/pwbm_sp_dev.egg-info/top_level.txt
src/sp_devtools/__init__.py
src/sp_devtools/__main__.py
src/sp_devtools/constants.py
src/sp_devtools/context.py
src/sp_devtools/models/__init__.py
src/sp_devtools/models/output_structure.py
src/sp_devtools/templates/__init__.py
src/sp_devtools/templates/base.py
src/sp_devtools/utils/__init__.py
src/sp_devtools/utils/run.py
src/sp_devtools/utils/template.py
src/sp_devtools/utils/wrap.py