Metadata-Version: 2.1
Name: pwbm-sp-dev
Version: 0.17.9
Summary: UNKNOWN
Home-page: UNKNOWN
License: UNKNOWN
Platform: UNKNOWN
Requires-Python: >=3.9
